LICENSE.txt
README.md
setup.py
mgc_python_package/__init__.py
mgc_python_package/__main__.py
mgc_python_package/workshops.py
mgc_python_package.egg-info/PKG-INFO
mgc_python_package.egg-info/SOURCES.txt
mgc_python_package.egg-info/dependency_links.txt
mgc_python_package.egg-info/entry_points.txt
mgc_python_package.egg-info/requires.txt
mgc_python_package.egg-info/top_level.txt