Metadata-Version: 2.1
Name: mgc-python-package
Version: 0.0.2
Summary: Permite consumir el API de CodigoFacilito
Home-page: https://github.com/marielaGutiCall/package-python
Author: Mariela Gutierrez Callejas
Author-email: mariela.guticall@gmail.com
License: MIT
Keywords: codigofacilito
Platform: UNKNOWN
Classifier: Development Status :: 3 - Alpha
Classifier: Intended Audience :: Developers
Classifier: Topic :: Software Development :: Build Tools
Classifier: License :: OSI Approved :: MIT License
Classifier: Programming Language :: Python :: 3
License-File: LICENSE.txt
